shelves_and_buckets/__init__.py
shelves_and_buckets/exceptions.py
shelves_and_buckets/shelves_and_buckets.py
shelves_and_buckets-0.1.4.dist-info/DESCRIPTION.rst
shelves_and_buckets-0.1.4.dist-info/METADATA
shelves_and_buckets-0.1.4.dist-info/RECORD
shelves_and_buckets-0.1.4.dist-info/WHEEL
shelves_and_buckets-0.1.4.dist-info/metadata.json
shelves_and_buckets-0.1.4.dist-info/top_level.txt
