Metadata-Version: 2.0
Name: shelves-and-buckets
Version: 0.1.4
Summary: Shelves and buckets for easier work with grouped data
Home-page: https://github.com/lifesum/shelves_and_buckets
Author: Ilian Stefkov Iliev
Author-email: ilian@ilian.io
License: MIT license
Keywords: shelves_and_buckets
Platform: UNKNOWN
Classifier: Development Status :: 2 - Pre-Alpha
Classifier: Intended Audience :: Developers
Classifier: License :: OSI Approved :: MIT License
Classifier: Natural Language :: English
Classifier: Programming Language :: Python :: 2
Classifier: Programming Language :: Python :: 2.6
Classifier: Programming Language :: Python :: 2.7
Classifier: Programming Language :: Python :: 3
Classifier: Programming Language :: Python :: 3.3
Classifier: Programming Language :: Python :: 3.4
Classifier: Programming Language :: Python :: 3.5
Requires-Dist: intervals
